pyUtilsKit/__init__.py
pyUtilsKit/dataValidator/__init__.py
pyUtilsKit/dateTimeUtils/__init__.py
pyUtilsKit/fileOperations/__init__.py
pyUtilsKit/httpUtils/__init__.py
pyUtilsKit/mathUtils/__init__.py
pyUtilsKit/passwordUtils/__init__.py
pyUtilsKit/randomData/__init__.py
pyUtilsKit/stringProcessor/__init__.py
pyUtilsKit/textAnalyzer/__init__.py
pyutilskit-1.0.0.dist-info/licenses/LICENCE
pyutilskit-1.0.0.dist-info/METADATA
pyutilskit-1.0.0.dist-info/WHEEL
pyutilskit-1.0.0.dist-info/top_level.txt
pyutilskit-1.0.0.dist-info/RECORD
