Metadata-Version: 2.4
Name: pyUtilsKit
Version: 1.0.0
Summary: 模块化设计的Python工具集合，提供日常开发中最常用的功能组件
Author-email: Jemy10000 <sh_ljr_2013@163.com>
License-Expression: MIT
Project-URL: Homepage, https://github.com/pypa/sampleproject
Project-URL: Issues, https://github.com/pypa/sampleproject/issues
Classifier: Programming Language :: Python :: 3
Classifier: Operating System :: OS Independent
Requires-Python: >=3.10
License-File: LICENCE
Dynamic: license-file
